{
    "members": [
        {
            "last_name": "Adner", 
            "national_id": null, 
            "class_year": 0, 
            "id": 10863222, 
            "city": "Damansara Heights", 
            "first_name": "Kayla", 
            "student_id": "20260001", 
            "zipcode": "50490", 
            "state": "Kuala Lumpur", 
            "program": null, 
            "language4": null, 
            "type": "Students", 
            "email": "Kayla.Adner026@igbis.edu.my", 
            "phone_number": "0320115001", 
            "parents_ids": [
                10863235, 
                10863241
            ], 
            "nationality2": null, 
            "nationality3": null, 
            "nationality1": "Sweden", 
            "mobile_phone_number": "", 
            "attendance_start_date": "2014-08-18", 
            "birthday": "2007-08-23", 
            "nationality4": null, 
            "openapply_parent_id": null, 
            "nickname": "Kayla", 
            "openapply_student_id": null, 
            "language": "en", 
            "gender": "Female", 
            "language3": null, 
            "language2": null, 
            "language1": null, 
            "street_address_ii": "", 
            "country": "MY", 
            "street_address": "54 Persiaran Bruas"
        }, 
        {
            "last_name": "Corbetta", 
            "national_id": null, 
            "class_year": 0, 
            "id": 10866874, 
            "city": "Sungai Buloh", 
            "first_name": "Beatrice", 
            "student_id": "20260002", 
            "zipcode": "47000", 
            "state": "Selangor", 
            "program": null, 
            "language4": null, 
            "type": "Students", 
            "email": "Beatrice.Corbetta026@igbis.edu.my", 
            "phone_number": "0136322609", 
            "parents_ids": [
                10866881, 
                10866882
            ], 
            "nationality2": null, 
            "nationality3": null, 
            "nationality1": "Italy", 
            "mobile_phone_number": "", 
            "attendance_start_date": "2014-08-18", 
            "birthday": "2008-09-09", 
            "nationality4": null, 
            "openapply_parent_id": null, 
            "nickname": "Beatrice", 
            "openapply_student_id": null, 
            "language": "en", 
            "gender": "Female", 
            "language3": null, 
            "language2": null, 
            "language1": null, 
            "street_address_ii": "Valancia", 
            "country": "MY", 
            "street_address": "No. 1 Elitis Ira Dedaun"
        }, 
        {
            "last_name": "Harvey", 
            "national_id": "", 
            "class_year": 0, 
            "id": 10834643, 
            "city": "Sungai Buloh", 
            "first_name": "Matilda", 
            "student_id": "20260003", 
            "zipcode": "47000", 
            "state": "Selangor", 
            "program": null, 
            "language4": "", 
            "type": "Students", 
            "email": "Matilda.Harvey026@igbis.edu.my", 
            "phone_number": "0129706297", 
            "parents_ids": [
                10868323, 
                10868324
            ], 
            "nationality2": "", 
            "nationality3": "", 
            "nationality1": "Australia", 
            "mobile_phone_number": "", 
            "attendance_start_date": "2014-08-18", 
            "birthday": "2007-11-28", 
            "nationality4": "", 
            "openapply_parent_id": null, 
            "nickname": "Tilly", 
            "openapply_student_id": null, 
            "language": "en", 
            "gender": "Female", 
            "language3": "", 
            "language2": "", 
            "language1": "", 
            "street_address_ii": "Valencia", 
            "country": "MY", 
            "street_address": "8 Jalan Elitis Tiara Utara"
        }, 
        {
            "last_name": "Marshall", 
            "national_id": null, 
            "class_year": 0, 
            "id": 10834651, 
            "city": "Desa Park City", 
            "first_name": "Nathan", 
            "student_id": "20260004", 
            "zipcode": "52200", 
            "state": "Kuala Lumpur", 
            "program": null, 
            "language4": null, 
            "type": "Students", 
            "email": "Nathan.Marshall026@igbis.edu.my", 
            "phone_number": "0125390244", 
            "parents_ids": [
                10868319, 
                10868320
            ], 
            "nationality2": null, 
            "nationality3": null, 
            "nationality1": "Canada", 
            "mobile_phone_number": "", 
            "attendance_start_date": "2014-08-18", 
            "birthday": "2007-10-11", 
            "nationality4": null, 
            "openapply_parent_id": null, 
            "nickname": "Nathan", 
            "openapply_student_id": null, 
            "language": "en", 
            "gender": "Male", 
            "language3": null, 
            "language2": null, 
            "language1": null, 
            "street_address_ii": "Safa Terraces", 
            "country": "MY", 
            "street_address": "7 Jalan Safa 3"
        }, 
        {
            "last_name": "Mohamed", 
            "national_id": "", 
            "class_year": 0, 
            "id": 10882224, 
            "city": "Mont Kiara", 
            "first_name": "Ainee", 
            "student_id": "20260005", 
            "zipcode": "50480", 
            "state": "Kuala Lumpur", 
            "program": null, 
            "language4": null, 
            "type": "Students", 
            "email": "Ainee.Mohamed026@igbis.edu.my", 
            "phone_number": "0362116593", 
            "parents_ids": [
                10872718, 
                10872719
            ], 
            "nationality2": null, 
            "nationality3": null, 
            "nationality1": "Maldives", 
            "mobile_phone_number": "", 
            "attendance_start_date": "2014-08-18", 
            "birthday": "2007-12-17", 
            "nationality4": null, 
            "openapply_parent_id": null, 
            "nickname": "Ainee", 
            "openapply_student_id": null, 
            "language": "en", 
            "gender": "Female", 
            "language3": null, 
            "language2": null, 
            "language1": null, 
            "street_address_ii": "32 Jalan Kiara", 
            "country": "MY", 
            "street_address": "B3-23A-2, MK28"
        }, 
        {
            "last_name": "Nanayakkara", 
            "national_id": null, 
            "class_year": 0, 
            "id": 10856823, 
            "city": "Sungai Buluh", 
            "first_name": "Aveesha", 
            "student_id": "20260006", 
            "zipcode": "47000", 
            "state": "Selangor", 
            "program": null, 
            "language4": null, 
            "type": "Students", 
            "email": "Aveesha.Nanayakkara026@igbis.edu.my", 
            "phone_number": "0133330199", 
            "parents_ids": [
                10868395, 
                10868396
            ], 
            "nationality2": null, 
            "nationality3": null, 
            "nationality1": "Sri lanka", 
            "mobile_phone_number": "", 
            "attendance_start_date": "2014-08-18", 
            "birthday": "2008-01-22", 
            "nationality4": null, 
            "openapply_parent_id": null, 
            "nickname": "Aveesha", 
            "openapply_student_id": null, 
            "language": "en", 
            "gender": "Female", 
            "language3": null, 
            "language2": null, 
            "language1": null, 
            "street_address_ii": "Valencia", 
            "country": "MY", 
            "street_address": "No.7, Elitis Laman Hijau"
        }, 
        {
            "last_name": "Smith", 
            "national_id": null, 
            "class_year": 0, 
            "id": 10834648, 
            "city": "Sungai Buloh", 
            "first_name": "Miah", 
            "student_id": "20260007", 
            "zipcode": "47000", 
            "state": "Selangor", 
            "program": null, 
            "language4": null, 
            "type": "Students", 
            "email": "Miah.Smith026@igbis.edu.my", 
            "phone_number": "None as yet", 
            "parents_ids": [
                10868356, 
                10868357
            ], 
            "nationality2": null, 
            "nationality3": null, 
            "nationality1": "Australia", 
            "mobile_phone_number": "", 
            "attendance_start_date": "2014-08-18", 
            "birthday": "2007-08-30", 
            "nationality4": null, 
            "openapply_parent_id": null, 
            "nickname": "Miah", 
            "openapply_student_id": null, 
            "language": "en", 
            "gender": "Female", 
            "language3": null, 
            "language2": null, 
            "language1": null, 
            "street_address_ii": "Valencia", 
            "country": "MY", 
            "street_address": "16 Elitis Tiara Utara "
        }, 
        {
            "last_name": "Fournier", 
            "national_id": null, 
            "class_year": null, 
            "id": 10912649, 
            "city": "Petaling Jaya", 
            "first_name": "Nina", 
            "student_id": "20260008", 
            "zipcode": "47410", 
            "state": "Selangor", 
            "program": null, 
            "language4": null, 
            "type": "Students", 
            "email": "Nina.Fournier026@igbis.edu.my", 
            "phone_number": "0122787778", 
            "parents_ids": [
                10912653, 
                11140737
            ], 
            "nationality2": null, 
            "nationality3": null, 
            "nationality1": "United states", 
            "mobile_phone_number": "", 
            "attendance_start_date": "2014-08-18", 
            "birthday": "2008-05-07", 
            "nationality4": null, 
            "openapply_parent_id": null, 
            "nickname": "Nina", 
            "openapply_student_id": null, 
            "language": "en", 
            "gender": "Female", 
            "language3": null, 
            "language2": null, 
            "language1": null, 
            "street_address_ii": "Tropicana Golf and Country Resort", 
            "country": "MY", 
            "street_address": "23 Jalan TR 7/2"
        }, 
        {
            "last_name": "Lai", 
            "national_id": "", 
            "class_year": null, 
            "id": 11124212, 
            "city": "Bandar Utama", 
            "first_name": "Alexander", 
            "student_id": "20260009", 
            "zipcode": "47800", 
            "state": "Selangor", 
            "program": null, 
            "language4": null, 
            "type": "Students", 
            "email": "alexander.lai026@igbis.edu.my", 
            "phone_number": "03-77132089", 
            "parents_ids": [
                11127748
            ], 
            "nationality2": null, 
            "nationality3": null, 
            "nationality1": "Malaysia", 
            "mobile_phone_number": "", 
            "attendance_start_date": "2015-01-07", 
            "birthday": "2007-12-15", 
            "nationality4": null, 
            "openapply_parent_id": null, 
            "nickname": "Alex", 
            "openapply_student_id": null, 
            "language": "en", 
            "gender": "Male", 
            "language3": null, 
            "language2": null, 
            "language1": null, 
            "street_address_ii": "No 3 Changkat Bukit Utama", 
            "country": "MY", 
            "street_address": "A1-25-1 Bukit Utama 1"
        }
    ]
}